uncertainty_wrapper/__init__.py
uncertainty_wrapper/core.py
uncertainty_wrapper/docs/Makefile
uncertainty_wrapper/docs/api.rst
uncertainty_wrapper/docs/conf.py
uncertainty_wrapper/docs/getting_started.rst
uncertainty_wrapper/docs/index.rst
uncertainty_wrapper/docs/make.bat
uncertainty_wrapper/tests/__init__.py
uncertainty_wrapper/tests/test_algopy.py
uncertainty_wrapper/tests/test_uncertainty_wrapper.py
UncertaintyWrapper-0.4.2.dist-info/LICENSE
UncertaintyWrapper-0.4.2.dist-info/METADATA
UncertaintyWrapper-0.4.2.dist-info/WHEEL
UncertaintyWrapper-0.4.2.dist-info/top_level.txt
UncertaintyWrapper-0.4.2.dist-info/RECORD
