Metadata-Version: 1.1
Name: UncertaintyWrapper
Version: 0.4.2
Summary: Uncertainty wrapper using estimated Jacobian
Home-page: https://github.com/BreakingBytes/UncertaintyWrapper
Author: Mark Mikofski
Author-email: bwana.marko@yahoo.com
License: UNKNOWN
Platform: UNKNOWN
Requires: numpy (>=1.8)
